QoolTabs
